driarxiv/__init__.py
driarxiv/build_readme.py
driarxiv/logger_config.py
driarxiv/run.py
driarxiv/worker.py
driarxiv/parser/__init__.py
driarxiv/parser/base.py
driarxiv/parser/pdf_worker.py
driarxiv-1.1.0.dist-info/METADATA
driarxiv-1.1.0.dist-info/WHEEL
driarxiv-1.1.0.dist-info/entry_points.txt
driarxiv-1.1.0.dist-info/top_level.txt
driarxiv-1.1.0.dist-info/RECORD
